calculator_mfelic/__init__.py
calculator_mfelic/calculator.py
calculator_mfelic-1.0.4.dist-info/entry_points.txt
calculator_mfelic-1.0.4.dist-info/WHEEL
calculator_mfelic-1.0.4.dist-info/METADATA
calculator_mfelic-1.0.4.dist-info/RECORD
